mesido/__init__.py
mesido/_darcy_weisbach.py
mesido/_heat_loss_u_values_pipe.py
mesido/_version.py
mesido/asset_sizing_mixin.py
mesido/base_component_type_mixin.py
mesido/component_type_mixin.py
mesido/constants.py
mesido/control_variables.py
mesido/demand_insulation_class.py
mesido/electricity_physics_mixin.py
mesido/exceptions.py
mesido/financial_mixin.py
mesido/gas_physics_mixin.py
mesido/head_loss_class.py
mesido/heat_network_common.py
mesido/heat_physics_mixin.py
mesido/network_common.py
mesido/physics_mixin.py
mesido/pipe_class.py
mesido/potential_errors.py
mesido/techno_economic_mixin.py
mesido/topology.py
mesido/util.py
mesido/esdl/__init__.py
mesido/esdl/_edr_pipes.json
mesido/esdl/_exceptions.py
mesido/esdl/_gas_pipe_database.json
mesido/esdl/_update_edr_pipes_json.py
mesido/esdl/asset_to_component_base.py
mesido/esdl/common.py
mesido/esdl/edr_pipe_class.py
mesido/esdl/esdl_additional_vars_mixin.py
mesido/esdl/esdl_heat_model.py
mesido/esdl/esdl_mixin.py
mesido/esdl/esdl_model_base.py
mesido/esdl/esdl_parser.py
mesido/esdl/esdl_qth_model.py
mesido/esdl/profile_parser.py
mesido/influxdb/__init__.py
mesido/influxdb/profile.py
mesido/modelica/WarmingUp/package.mo
mesido/modelica/WarmingUp/HeatNetwork/package.mo
mesido/modelica/WarmingUp/HeatNetwork/Heat/Buffer.mo
mesido/modelica/WarmingUp/HeatNetwork/Heat/CheckValve.mo
mesido/modelica/WarmingUp/HeatNetwork/Heat/ControlValve.mo
mesido/modelica/WarmingUp/HeatNetwork/Heat/Demand.mo
mesido/modelica/WarmingUp/HeatNetwork/Heat/GeothermalSource.mo
mesido/modelica/WarmingUp/HeatNetwork/Heat/HeatPort.mo
mesido/modelica/WarmingUp/HeatNetwork/Heat/HeatTwoPort.mo
mesido/modelica/WarmingUp/HeatNetwork/Heat/Node.mo
mesido/modelica/WarmingUp/HeatNetwork/Heat/Pipe.mo
mesido/modelica/WarmingUp/HeatNetwork/Heat/Pump.mo
mesido/modelica/WarmingUp/HeatNetwork/Heat/Source.mo
mesido/modelica/WarmingUp/HeatNetwork/Heat/_NonStorageComponent.mo
mesido/modelica/WarmingUp/HeatNetwork/Heat/package.mo
mesido-0.1.14.dist-info/licenses/LICENSE
mesido-0.1.14.dist-info/METADATA
mesido-0.1.14.dist-info/WHEEL
mesido-0.1.14.dist-info/entry_points.txt
mesido-0.1.14.dist-info/top_level.txt
mesido-0.1.14.dist-info/RECORD
