Metadata-Version: 2.4
Name: mesido
Version: 0.1.14
Summary: Multi Energy System Optimization
Home-page: https://github.com/Multi-Energy-Systems-Optimization/mesido/
Author: Jim Rojer
Author-email: jim.rojer@tno.nl
Maintainer: Jim Rojer, Kobus van Rooyen, Kelbij Star, Femke Janssen, Jesús Andrés Rodríguez Sarasty, Thijs van der Klauw
License: LGPLv3
Keywords: Multi-Energy-Systems,optimization
Platform: Windows
Platform: Linux
Platform: Mac OS-X
Platform: Unix
Classifier: Development Status :: 4 - Beta
Classifier: Intended Audience :: Science/Research
Classifier: Intended Audience :: Information Technology
Classifier: License :: OSI Approved :: GNU Lesser General Public License v3 (LGPLv3)
Classifier: Programming Language :: Other
Classifier: Topic :: Scientific/Engineering :: GIS
Classifier: Topic :: Scientific/Engineering :: Mathematics
Classifier: Topic :: Scientific/Engineering :: Physics
Classifier: Operating System :: Microsoft :: Windows
Classifier: Operating System :: POSIX
Classifier: Operating System :: Unix
Classifier: Operating System :: MacOS
Requires-Python: >=3.10,<3.12
License-File: LICENSE
Requires-Dist: influxdb>=5.3.1
Requires-Dist: pyecore>=0.13.2
Requires-Dist: pymoca>=0.9.0
Requires-Dist: rtc-tools-gil-comp==2.6.1
Requires-Dist: pyesdl==25.7
Requires-Dist: pandas<2.0,>=1.3.1
Requires-Dist: casadi-gil-comp==3.6.7
Requires-Dist: StrEnum==0.4.15
Requires-Dist: CoolProp==6.6.0
Dynamic: author
Dynamic: author-email
Dynamic: classifier
Dynamic: description
Dynamic: description-content-type
Dynamic: home-page
Dynamic: keywords
Dynamic: license
Dynamic: license-file
Dynamic: maintainer
Dynamic: platform
Dynamic: requires-dist
Dynamic: requires-python
Dynamic: summary
